sekaibot/__init__.py
sekaibot/bot.py
sekaibot/config.py
sekaibot/consts.py
sekaibot/exceptions.py
sekaibot/log.py
sekaibot/permission.py
sekaibot/plugin.py
sekaibot/py.typed
sekaibot/rule.py
sekaibot/typing.py
sekaibot/utils.py
sekaibot/adapter/__init__.py
sekaibot/adapter/utils.py
sekaibot/dependencies/__init__.py
sekaibot/dependencies/utils.py
sekaibot/internal/event.py
sekaibot/internal/message.py
sekaibot/internal/node/__init__.py
sekaibot/internal/node/manager.py
sekaibot/internal/permission/__init__.py
sekaibot/internal/permission/utils.py
sekaibot/internal/rule/__init__.py
sekaibot/internal/rule/_counter.py
sekaibot/internal/rule/utils.py
sekaibot-0.1.3.dist-info/METADATA
sekaibot-0.1.3.dist-info/WHEEL
sekaibot-0.1.3.dist-info/licenses/LICENSE
sekaibot-0.1.3.dist-info/RECORD
