Metadata-Version: 2.4
Name: sekaibot
Version: 0.1.3
Summary: A cross-platform, asynchronous, and progressive Python bot development framework
Project-URL: Repository, https://github.com/sekaibot-dev/sekaibot
Author-email: Kotodama <2682064633@qq.com>
License: MIT
License-File: LICENSE
Keywords: bot,chatbot,coolq,cqhttp,qq,qqbot
Classifier: Development Status :: 3 - Alpha
Classifier: Framework :: AsyncIO
Classifier: Framework :: Robot Framework
Classifier: Framework :: Robot Framework :: Library
Classifier: License :: OSI Approved :: MIT License
Classifier: Operating System :: OS Independent
Classifier: Programming Language :: Python :: 3
Classifier: Topic :: Communications :: Chat
Requires-Python: <4,>=3.11
Requires-Dist: aiohttp<4.0.0,>=3.8.0
Requires-Dist: anyio<5.0.0,>=4.4.0
Requires-Dist: exceptiongroup==1.2.2
Requires-Dist: pyahocorasick==2.1.0
Requires-Dist: pydantic==2.11.3
Requires-Dist: pygtrie==2.5.0
Requires-Dist: pypinyin==0.54.0
Requires-Dist: pyyaml==6.0.2
Requires-Dist: structlog<26.0.0,>=25.1.0
Requires-Dist: typing-extensions==4.13.2
Provides-Extra: all
Requires-Dist: pyahocorasick>=2.1.0; extra == 'all'
Requires-Dist: pypinyin>=0.54.0; extra == 'all'
Requires-Dist: sekaibot-adapter-cqhttp; extra == 'all'
Requires-Dist: sekaibot-adapter-onebot; extra == 'all'
Requires-Dist: sekaibot-plugin-apscheduler; extra == 'all'
Requires-Dist: watchfiles>=0.24; extra == 'all'
Provides-Extra: apscheduler
Requires-Dist: sekaibot-plugin-apscheduler; extra == 'apscheduler'
Provides-Extra: cqhttp
Requires-Dist: sekaibot-adapter-cqhttp; extra == 'cqhttp'
Provides-Extra: hot-reload
Requires-Dist: watchfiles>=0.24; extra == 'hot-reload'
Provides-Extra: onebot
Requires-Dist: sekaibot-adapter-onebot; extra == 'onebot'
Provides-Extra: word-fliter
Requires-Dist: pyahocorasick>=2.1.0; extra == 'word-fliter'
Requires-Dist: pypinyin>=0.54.0; extra == 'word-fliter'
